pyTrigger.py
pytrigger-0.12.2.dist-info/METADATA
pytrigger-0.12.2.dist-info/WHEEL
pytrigger-0.12.2.dist-info/licenses/LICENSE
pytrigger-0.12.2.dist-info/RECORD
